data_refinery-0.2.13.dist-info/METADATA
data_refinery-0.2.13.dist-info/RECORD
data_refinery-0.2.13.dist-info/WHEEL
data_refinery-0.2.13.dist-info/top_level.txt
datarefinery/CombineOperations.py
datarefinery/DateFieldOperations.py
datarefinery/FieldOperations.py
datarefinery/TupleOperations.py
datarefinery/__init__.py
datarefinery/tuple/Formats.py
datarefinery/tuple/TupleDSL.py
datarefinery/tuple/__init__.py
tests/examples/__init__.py
tests/examples/test_pandas_operations.py
tests/tuple/__init__.py
tests/tuple/test_alternative.py
tests/tuple/test_append.py
tests/tuple/test_filter.py
tests/tuple/test_fusion.py
tests/tuple/test_fusion_append.py
tests/tuple/test_keep.py
tests/tuple/test_keep_regexp.py
tests/tuple/test_substitution.py
