Metadata-Version: 2.1
Name: data-refinery
Version: 0.2.13
Summary: Data Refinery: transformating data
Home-page: https://github.com/BBVA/data-refinery
Author: BBVA
Author-email: cesar.gallego@bbva.com, leticia.garcia3@bbva.com
Maintainer-email: cesar.gallego@bbva.com
License: Apache 2.0
Platform: UNKNOWN
Classifier: License :: OSI Approved :: Apache Software License
Classifier: Programming Language :: Python :: 3.5
Classifier: Programming Language :: Python :: 3.6
Classifier: Topic :: Software Development :: Libraries :: Python Modules
Classifier: Topic :: Scientific/Engineering :: Artificial Intelligence
Classifier: Topic :: Scientific/Engineering :: Information Analysis
Requires-Python: >=3.5
